pymt_permamodel/__init__.py
pymt_permamodel/bmi.py
pymt_permamodel/data/FrostNumber/api.yaml
pymt_permamodel/data/FrostNumber/fn_t_air_max.dat
pymt_permamodel/data/FrostNumber/fn_t_air_min.dat
pymt_permamodel/data/FrostNumber/frostnumber_model.cfg
pymt_permamodel/data/FrostNumber/info.yaml
pymt_permamodel/data/FrostNumber/parameters.yaml
pymt_permamodel/data/FrostNumber/run.yaml
pymt_permamodel/data/Ku/A_air.txt
pymt_permamodel/data/Ku/T_air.txt
pymt_permamodel/data/Ku/api.yaml
pymt_permamodel/data/Ku/dvf.txt
pymt_permamodel/data/Ku/dvt.txt
pymt_permamodel/data/Ku/h_snow.txt
pymt_permamodel/data/Ku/hvgf.txt
pymt_permamodel/data/Ku/hvgt.txt
pymt_permamodel/data/Ku/info.yaml
pymt_permamodel/data/Ku/ku_model.cfg
pymt_permamodel/data/Ku/parameters.yaml
pymt_permamodel/data/Ku/rho_snow.txt
pymt_permamodel/data/Ku/run.yaml
pymt_permamodel/data/Ku/vwc.txt
pymt_permamodel/data/KuEnhanced/air_temperature.nc
pymt_permamodel/data/KuEnhanced/api.yaml
pymt_permamodel/data/KuEnhanced/frozen_vegetation_diffusivity.nc
pymt_permamodel/data/KuEnhanced/frozen_vegetation_height.nc
pymt_permamodel/data/KuEnhanced/info.yaml
pymt_permamodel/data/KuEnhanced/ku_config.toml
pymt_permamodel/data/KuEnhanced/parameters.yaml
pymt_permamodel/data/KuEnhanced/run.yaml
pymt_permamodel/data/KuEnhanced/snow_density.nc
pymt_permamodel/data/KuEnhanced/snow_thickness.nc
pymt_permamodel/data/KuEnhanced/soil_water_content.nc
pymt_permamodel/data/KuEnhanced/temperature_amplitude.nc
pymt_permamodel/data/KuEnhanced/thawed_vegetation_diffusivity.nc
pymt_permamodel/data/KuEnhanced/thawed_vegetation_height.nc
pymt_permamodel-0.2.3.dist-info/LICENSE
pymt_permamodel-0.2.3.dist-info/METADATA
pymt_permamodel-0.2.3.dist-info/WHEEL
pymt_permamodel-0.2.3.dist-info/entry_points.txt
pymt_permamodel-0.2.3.dist-info/top_level.txt
pymt_permamodel-0.2.3.dist-info/RECORD
