Metadata-Version: 2.1
Name: pymt_permamodel
Version: 0.2.3
Summary: PyMT plugin for pymt_permamodel
Home-page: https://github.com/pymt-lab/pymt_permamodel
Author: CSDMS
Author-email: csdms@colorado.edu
Keywords: bmi,pymt
Classifier: Development Status :: 4 - Beta
Classifier: Intended Audience :: Science/Research
Classifier: License :: OSI Approved :: MIT License
Classifier: Operating System :: MacOS :: MacOS X
Classifier: Operating System :: POSIX :: Linux
Classifier: Programming Language :: Python :: 3 :: Only
License-File: LICENSE
Requires-Dist: numpy
